seamless/__init__.py
seamless/errors.py
seamless/version.py
seamless/components/__init__.py
seamless/components/page.py
seamless/components/router/__init__.py
seamless/components/router/route.py
seamless/components/router/router.js
seamless/components/router/router.py
seamless/components/router/router_link.py
seamless/context/__init__.py
seamless/context/context.py
seamless/context/default.py
seamless/core/__init__.py
seamless/core/empty.py
seamless/core/javascript.py
seamless/extensions/__init__.py
seamless/extensions/state.py
seamless/extensions/transports.py
seamless/extra/__init__.py
seamless/extra/feature.py
seamless/extra/components/__init__.py
seamless/extra/components/repository.py
seamless/extra/events/__init__.py
seamless/extra/events/database.py
seamless/extra/events/errors.py
seamless/extra/events/transformers.py
seamless/extra/state/__init__.py
seamless/extra/state/state.get.js
seamless/extra/state/state.init.js
seamless/extra/transformers/js_transformer.py
seamless/extra/transports/client_id.py
seamless/extra/transports/dispatcher.py
seamless/extra/transports/errors.py
seamless/extra/transports/subscriptable.py
seamless/extra/transports/transport.py
seamless/extra/transports/socketio/middleware.py
seamless/extra/transports/socketio/socketio.init.js
seamless/extra/transports/socketio/transport.py
seamless/html/__init__.py
seamless/html/__init__.pyi
seamless/html/a.pyi
seamless/html/abbr.pyi
seamless/html/address.pyi
seamless/html/area.pyi
seamless/html/article.pyi
seamless/html/aside.pyi
seamless/html/audio.pyi
seamless/html/b.pyi
seamless/html/base.pyi
seamless/html/bdi.pyi
seamless/html/bdo.pyi
seamless/html/blockquote.pyi
seamless/html/body.pyi
seamless/html/br.pyi
seamless/html/button.pyi
seamless/html/canvas.pyi
seamless/html/caption.pyi
seamless/html/cite.pyi
seamless/html/code.pyi
seamless/html/col.pyi
seamless/html/colgroup.pyi
seamless/html/data.pyi
seamless/html/datalist.pyi
seamless/html/dd.pyi
seamless/html/del_.pyi
python_seamless-0.9.3.dist-info/LICENSE
python_seamless-0.9.3.dist-info/METADATA
python_seamless-0.9.3.dist-info/WHEEL
python_seamless-0.9.3.dist-info/top_level.txt
python_seamless-0.9.3.dist-info/RECORD
