Metadata-Version: 2.1
Name: python-seamless
Version: 0.9.3
Summary: A Python package for creating and manipulating HTML components. It is working similar to React.js, but in Python
Author-email: Xpo Development <dev@xpo.dev>
Project-URL: Homepage, https://github.com/xpodev/seamless
Project-URL: Issues, https://github.com/xpodev/seamless/issues
Classifier: Programming Language :: Python :: 3
Classifier: License :: OSI Approved :: MIT License
Classifier: Operating System :: OS Independent
Requires-Python: >=3.11
License-File: LICENSE
Requires-Dist: cssutils==2.9.0
Requires-Dist: python-dom
Requires-Dist: python-socketio==5.11.1
Requires-Dist: typing-extensions
